es/__init__.py
es/baseapi.py
es/basesqlalchemy.py
es/const.py
es/exceptions.py
es/__pycache__/__init__.cpython-37.pyc
es/__pycache__/baseapi.cpython-37.pyc
es/__pycache__/basesqlalchemy.cpython-37.pyc
es/__pycache__/const.cpython-37.pyc
es/__pycache__/exceptions.cpython-37.pyc
es/elastic/__init__.py
es/elastic/api.py
es/elastic/sqlalchemy.py
es/elastic/__pycache__/__init__.cpython-37.pyc
es/elastic/__pycache__/api.cpython-37.pyc
es/elastic/__pycache__/sqlalchemy.cpython-37.pyc
es/opendistro/__init__.py
es/opendistro/api.py
es/opendistro/sqlalchemy.py
es/opendistro/__pycache__/__init__.cpython-37.pyc
es/opendistro/__pycache__/api.cpython-37.pyc
es/opendistro/__pycache__/sqlalchemy.cpython-37.pyc
es/tests/__init__.py
es/tests/test_0_fixtures.py
es/tests/test_dbapi.py
es/tests/test_sqlalchemy.py
es/tests/__pycache__/__init__.cpython-37.pyc
es/tests/__pycache__/test_0_fixtures.cpython-37-pytest-7.2.1.pyc
es/tests/__pycache__/test_dbapi.cpython-37-pytest-7.2.1.pyc
es/tests/__pycache__/test_sqlalchemy.cpython-37-pytest-7.2.1.pyc
es/tests/fixtures/__init__.py
es/tests/fixtures/data1.json
es/tests/fixtures/data1_mappings.json
es/tests/fixtures/fixtures.py
es/tests/fixtures/flights.json
es/tests/fixtures/__pycache__/__init__.cpython-37.pyc
es/tests/fixtures/__pycache__/fixtures.cpython-37.pyc
elasticsearch_dbapi-0.2.10.dist-info/LICENSE.txt
elasticsearch_dbapi-0.2.10.dist-info/METADATA
elasticsearch_dbapi-0.2.10.dist-info/WHEEL
elasticsearch_dbapi-0.2.10.dist-info/entry_points.txt
elasticsearch_dbapi-0.2.10.dist-info/top_level.txt
elasticsearch_dbapi-0.2.10.dist-info/RECORD
